neko_aa/__init__.py
neko_aa-0.1.0.dist-info/METADATA
neko_aa-0.1.0.dist-info/WHEEL
neko_aa-0.1.0.dist-info/RECORD
