Metadata-Version: 2.1
Name: neko-aa
Version: 0.1.0
Summary: 猫のAAを簡単に出力できます。
Author: Same
Author-email: OsakanaFactory@gmail.com
Requires-Python: >=3.12,<4.0
Classifier: Programming Language :: Python :: 3
Classifier: Programming Language :: Python :: 3.12
